livevox_api/__init__.py
livevox_api/livevox_pypi.py
livevox_pypi-0.9.dist-info/LICENSE
livevox_pypi-0.9.dist-info/METADATA
livevox_pypi-0.9.dist-info/WHEEL
livevox_pypi-0.9.dist-info/top_level.txt
livevox_pypi-0.9.dist-info/RECORD
